LICENSE.txt
README.rst
setup.py
exectools/__init__.py
exectools/exectools.py
exectools.egg-info/PKG-INFO
exectools.egg-info/SOURCES.txt
exectools.egg-info/dependency_links.txt
exectools.egg-info/top_level.txt